fanshim/__init__.py
fanshim-0.0.5.dist-info/LICENSE.txt
fanshim-0.0.5.dist-info/METADATA
fanshim-0.0.5.dist-info/WHEEL
fanshim-0.0.5.dist-info/top_level.txt
fanshim-0.0.5.dist-info/RECORD
